<?xml version="1.0" ?>
<annotation>
	<folder>VideoData</folder>
	<source>
		<database>Video Data</database>
		<annotation>PASCAL 2012</annotation>
	</source>
	<owner>
		<name>samuel</name>
	</owner>
	<size>
		<width>1920</width>
		<height>1080</height>
		<depth>3</depth>
	</size>
	<segmented>0</segmented>
	<object>
		<name>person</name>
		<pose>Unspecified</pose>
		<truncated>0</truncated>
		<difficult>0</difficult>
		<occluded>0</occluded>
		<confidence>1</confidence>
		<bndbox>
			<xmin>1045</xmin>
			<ymin>18</ymin>
			<xmax>1114</xmax>
			<ymax>78</ymax>
		</bndbox>
		<keypoints>
			<cent_x>1087.0</cent_x>
			<cent_y>39.0</cent_y>
			<left_shoulder_x>-1.0</left_shoulder_x>
			<left_shoulder_y>-1.0</left_shoulder_y>
			<right_shoulder_x>1074.0</right_shoulder_x>
			<right_shoulder_y>61.0</right_shoulder_y>
			<neck_x>1068.0</neck_x>
			<neck_y>47.0</neck_y>
		</keypoints>
	</object>
	<object>
		<name>person</name>
		<pose>Unspecified</pose>
		<truncated>0</truncated>
		<difficult>0</difficult>
		<occluded>0</occluded>
		<confidence>1</confidence>
		<bndbox>
			<xmin>1234</xmin>
			<ymin>48</ymin>
			<xmax>1308</xmax>
			<ymax>97</ymax>
		</bndbox>
		<keypoints>
			<cent_x>1281.0</cent_x>
			<cent_y>81.0</cent_y>
			<left_shoulder_x>1247.0</left_shoulder_x>
			<left_shoulder_y>82.0</left_shoulder_y>
			<right_shoulder_x>1293.2</right_shoulder_x>
			<right_shoulder_y>87.2</right_shoulder_y>
			<neck_x>1271.0</neck_x>
			<neck_y>87.2</neck_y>
		</keypoints>
	</object>
	<object>
		<name>person</name>
		<pose>Unspecified</pose>
		<truncated>0</truncated>
		<difficult>0</difficult>
		<occluded>0</occluded>
		<confidence>1</confidence>
		<bndbox>
			<xmin>1184</xmin>
			<ymin>39</ymin>
			<xmax>1250</xmax>
			<ymax>101</ymax>
		</bndbox>
		<keypoints>
			<cent_x>1219.0</cent_x>
			<cent_y>54.0</cent_y>
			<left_shoulder_x>1192.0</left_shoulder_x>
			<left_shoulder_y>82.0</left_shoulder_y>
			<right_shoulder_x>1227.0</right_shoulder_x>
			<right_shoulder_y>79.0</right_shoulder_y>
			<neck_x>1216.0</neck_x>
			<neck_y>67.0</neck_y>
		</keypoints>
	</object>
	<object>
		<name>person</name>
		<pose>Unspecified</pose>
		<truncated>0</truncated>
		<difficult>0</difficult>
		<occluded>0</occluded>
		<confidence>1</confidence>
		<bndbox>
			<xmin>1348</xmin>
			<ymin>63</ymin>
			<xmax>1417</xmax>
			<ymax>115</ymax>
		</bndbox>
		<keypoints>
			<cent_x>1378.0</cent_x>
			<cent_y>82.0</cent_y>
			<left_shoulder_x>1361.8</left_shoulder_x>
			<left_shoulder_y>104.6</left_shoulder_y>
			<right_shoulder_x>1403.2</right_shoulder_x>
			<right_shoulder_y>104.6</right_shoulder_y>
			<neck_x>1383.0</neck_x>
			<neck_y>100.0</neck_y>
		</keypoints>
	</object>
	<object>
		<name>person</name>
		<pose>Unspecified</pose>
		<truncated>0</truncated>
		<difficult>0</difficult>
		<occluded>0</occluded>
		<confidence>1</confidence>
		<bndbox>
			<xmin>1374</xmin>
			<ymin>57</ymin>
			<xmax>1420</xmax>
			<ymax>106</ymax>
		</bndbox>
		<keypoints>
			<cent_x>1390.0</cent_x>
			<cent_y>74.0</cent_y>
			<left_shoulder_x>-1.0</left_shoulder_x>
			<left_shoulder_y>-1.0</left_shoulder_y>
			<right_shoulder_x>1410.0</right_shoulder_x>
			<right_shoulder_y>92.0</right_shoulder_y>
			<neck_x>1395.0</neck_x>
			<neck_y>92.0</neck_y>
		</keypoints>
	</object>
	<object>
		<name>person</name>
		<pose>Unspecified</pose>
		<truncated>0</truncated>
		<difficult>0</difficult>
		<occluded>0</occluded>
		<confidence>1</confidence>
		<bndbox>
			<xmin>1408</xmin>
			<ymin>67</ymin>
			<xmax>1469</xmax>
			<ymax>111</ymax>
		</bndbox>
		<keypoints>
			<cent_x>1438.5</cent_x>
			<cent_y>84.6</cent_y>
			<left_shoulder_x>-1.0</left_shoulder_x>
			<left_shoulder_y>-1.0</left_shoulder_y>
			<right_shoulder_x>1465.61111111</right_shoulder_x>
			<right_shoulder_y>101.0</right_shoulder_y>
			<neck_x>1438.5</neck_x>
			<neck_y>102.2</neck_y>
		</keypoints>
	</object>
	<object>
		<name>person</name>
		<pose>Unspecified</pose>
		<truncated>0</truncated>
		<difficult>0</difficult>
		<occluded>0</occluded>
		<confidence>1</confidence>
		<bndbox>
			<xmin>1424</xmin>
			<ymin>40</ymin>
			<xmax>1475</xmax>
			<ymax>83</ymax>
		</bndbox>
		<keypoints>
			<cent_x>1449.5</cent_x>
			<cent_y>57.2</cent_y>
			<left_shoulder_x>1434.2</left_shoulder_x>
			<left_shoulder_y>74.4</left_shoulder_y>
			<right_shoulder_x>1464.8</right_shoulder_x>
			<right_shoulder_y>74.4</right_shoulder_y>
			<neck_x>1449.5</neck_x>
			<neck_y>74.4</neck_y>
		</keypoints>
	</object>
	<object>
		<name>person</name>
		<pose>Unspecified</pose>
		<truncated>0</truncated>
		<difficult>0</difficult>
		<occluded>0</occluded>
		<confidence>1</confidence>
		<bndbox>
			<xmin>1477</xmin>
			<ymin>53</ymin>
			<xmax>1529</xmax>
			<ymax>102</ymax>
		</bndbox>
		<keypoints>
			<cent_x>1503.0</cent_x>
			<cent_y>72.6</cent_y>
			<left_shoulder_x>1487.4</left_shoulder_x>
			<left_shoulder_y>92.2</left_shoulder_y>
			<right_shoulder_x>1518.6</right_shoulder_x>
			<right_shoulder_y>92.2</right_shoulder_y>
			<neck_x>1503.0</neck_x>
			<neck_y>86.0</neck_y>
		</keypoints>
	</object>
	<object>
		<name>person</name>
		<pose>Unspecified</pose>
		<truncated>0</truncated>
		<difficult>0</difficult>
		<occluded>0</occluded>
		<confidence>1</confidence>
		<bndbox>
			<xmin>1653</xmin>
			<ymin>121</ymin>
			<xmax>1744</xmax>
			<ymax>180</ymax>
		</bndbox>
		<keypoints>
			<cent_x>1711.0</cent_x>
			<cent_y>150.0</cent_y>
			<left_shoulder_x>1675.0</left_shoulder_x>
			<left_shoulder_y>157.0</left_shoulder_y>
			<right_shoulder_x>-1.0</right_shoulder_x>
			<right_shoulder_y>-1.0</right_shoulder_y>
			<neck_x>1697.0</neck_x>
			<neck_y>169.0</neck_y>
		</keypoints>
	</object>
</annotation>
