<?xml version="1.0" ?>
<annotation>
	<folder>VideoData</folder>
	<source>
		<database>Video Data</database>
		<annotation>PASCAL 2012</annotation>
	</source>
	<owner>
		<name>samuel</name>
	</owner>
	<size>
		<width>1920</width>
		<height>1080</height>
		<depth>3</depth>
	</size>
	<segmented>0</segmented>
	<object>
		<name>person</name>
		<pose>Unspecified</pose>
		<truncated>0</truncated>
		<difficult>0</difficult>
		<occluded>0</occluded>
		<confidence>1</confidence>
		<bndbox>
			<xmin>918</xmin>
			<ymin>3</ymin>
			<xmax>980</xmax>
			<ymax>43</ymax>
		</bndbox>
		<keypoints>
			<cent_x>949.0</cent_x>
			<cent_y>19.0</cent_y>
			<left_shoulder_x>930.4</left_shoulder_x>
			<left_shoulder_y>35.0</left_shoulder_y>
			<right_shoulder_x>967.6</right_shoulder_x>
			<right_shoulder_y>35.0</right_shoulder_y>
			<neck_x>949.0</neck_x>
			<neck_y>35.0</neck_y>
		</keypoints>
	</object>
	<object>
		<name>person</name>
		<pose>Unspecified</pose>
		<truncated>0</truncated>
		<difficult>0</difficult>
		<occluded>0</occluded>
		<confidence>1</confidence>
		<bndbox>
			<xmin>1007</xmin>
			<ymin>17</ymin>
			<xmax>1064</xmax>
			<ymax>57</ymax>
		</bndbox>
		<keypoints>
			<cent_x>1035.5</cent_x>
			<cent_y>33.0</cent_y>
			<left_shoulder_x>1018.4</left_shoulder_x>
			<left_shoulder_y>49.0</left_shoulder_y>
			<right_shoulder_x>1052.6</right_shoulder_x>
			<right_shoulder_y>49.0</right_shoulder_y>
			<neck_x>1035.5</neck_x>
			<neck_y>49.0</neck_y>
		</keypoints>
	</object>
	<object>
		<name>person</name>
		<pose>Unspecified</pose>
		<truncated>0</truncated>
		<difficult>0</difficult>
		<occluded>0</occluded>
		<confidence>1</confidence>
		<bndbox>
			<xmin>1121</xmin>
			<ymin>25</ymin>
			<xmax>1183</xmax>
			<ymax>80</ymax>
		</bndbox>
		<keypoints>
			<cent_x>1152.0</cent_x>
			<cent_y>47.0</cent_y>
			<left_shoulder_x>1133.4</left_shoulder_x>
			<left_shoulder_y>69.0</left_shoulder_y>
			<right_shoulder_x>-1.0</right_shoulder_x>
			<right_shoulder_y>-1.0</right_shoulder_y>
			<neck_x>1152.0</neck_x>
			<neck_y>69.0</neck_y>
		</keypoints>
	</object>
	<object>
		<name>person</name>
		<pose>Unspecified</pose>
		<truncated>0</truncated>
		<difficult>0</difficult>
		<occluded>0</occluded>
		<confidence>1</confidence>
		<bndbox>
			<xmin>1241</xmin>
			<ymin>26</ymin>
			<xmax>1280</xmax>
			<ymax>69</ymax>
		</bndbox>
		<keypoints>
			<cent_x>1260.5</cent_x>
			<cent_y>43.2</cent_y>
			<left_shoulder_x>1248.8</left_shoulder_x>
			<left_shoulder_y>60.4</left_shoulder_y>
			<right_shoulder_x>1272.2</right_shoulder_x>
			<right_shoulder_y>60.4</right_shoulder_y>
			<neck_x>1260.5</neck_x>
			<neck_y>60.4</neck_y>
		</keypoints>
	</object>
	<object>
		<name>person</name>
		<pose>Unspecified</pose>
		<truncated>0</truncated>
		<difficult>0</difficult>
		<occluded>0</occluded>
		<confidence>1</confidence>
		<bndbox>
			<xmin>1301</xmin>
			<ymin>23</ymin>
			<xmax>1358</xmax>
			<ymax>65</ymax>
		</bndbox>
		<keypoints>
			<cent_x>1329.5</cent_x>
			<cent_y>39.8</cent_y>
			<left_shoulder_x>1312.4</left_shoulder_x>
			<left_shoulder_y>56.6</left_shoulder_y>
			<right_shoulder_x>1346.6</right_shoulder_x>
			<right_shoulder_y>56.6</right_shoulder_y>
			<neck_x>1329.5</neck_x>
			<neck_y>56.6</neck_y>
		</keypoints>
	</object>
	<object>
		<name>person</name>
		<pose>Unspecified</pose>
		<truncated>0</truncated>
		<difficult>0</difficult>
		<occluded>0</occluded>
		<confidence>1</confidence>
		<bndbox>
			<xmin>1339</xmin>
			<ymin>8</ymin>
			<xmax>1396</xmax>
			<ymax>63</ymax>
		</bndbox>
		<keypoints>
			<cent_x>1367.5</cent_x>
			<cent_y>30.0</cent_y>
			<left_shoulder_x>1350.4</left_shoulder_x>
			<left_shoulder_y>52.0</left_shoulder_y>
			<right_shoulder_x>1384.6</right_shoulder_x>
			<right_shoulder_y>52.0</right_shoulder_y>
			<neck_x>1367.5</neck_x>
			<neck_y>52.0</neck_y>
		</keypoints>
	</object>
	<object>
		<name>person</name>
		<pose>Unspecified</pose>
		<truncated>0</truncated>
		<difficult>0</difficult>
		<occluded>0</occluded>
		<confidence>1</confidence>
		<bndbox>
			<xmin>1398</xmin>
			<ymin>32</ymin>
			<xmax>1437</xmax>
			<ymax>82</ymax>
		</bndbox>
		<keypoints>
			<cent_x>1417.5</cent_x>
			<cent_y>52.0</cent_y>
			<left_shoulder_x>1405.8</left_shoulder_x>
			<left_shoulder_y>72.0</left_shoulder_y>
			<right_shoulder_x>1429.2</right_shoulder_x>
			<right_shoulder_y>72.0</right_shoulder_y>
			<neck_x>1417.5</neck_x>
			<neck_y>72.0</neck_y>
		</keypoints>
	</object>
	<object>
		<name>person</name>
		<pose>Unspecified</pose>
		<truncated>0</truncated>
		<difficult>0</difficult>
		<occluded>0</occluded>
		<confidence>1</confidence>
		<bndbox>
			<xmin>1369</xmin>
			<ymin>130</ymin>
			<xmax>1413</xmax>
			<ymax>173</ymax>
		</bndbox>
		<keypoints>
			<cent_x>1391.0</cent_x>
			<cent_y>147.2</cent_y>
			<left_shoulder_x>-1.0</left_shoulder_x>
			<left_shoulder_y>-1.0</left_shoulder_y>
			<right_shoulder_x>1404.2</right_shoulder_x>
			<right_shoulder_y>164.4</right_shoulder_y>
			<neck_x>1391.0</neck_x>
			<neck_y>164.4</neck_y>
		</keypoints>
	</object>
</annotation>
