<?xml version="1.0" ?>
<annotation>
	<folder>VideoData</folder>
	<source>
		<database>Video Data</database>
		<annotation>PASCAL 2012</annotation>
	</source>
	<owner>
		<name>samuel</name>
	</owner>
	<size>
		<width>1920</width>
		<height>1080</height>
		<depth>3</depth>
	</size>
	<segmented>0</segmented>
	<object>
		<name>person</name>
		<pose>Unspecified</pose>
		<truncated>0</truncated>
		<difficult>0</difficult>
		<occluded>0</occluded>
		<confidence>1</confidence>
		<bndbox>
			<xmin>1247</xmin>
			<ymin>194</ymin>
			<xmax>1364</xmax>
			<ymax>306</ymax>
		</bndbox>
		<keypoints>
			<cent_x>1308.0</cent_x>
			<cent_y>232.0</cent_y>
			<left_shoulder_x>1252.46728972</left_shoulder_x>
			<left_shoulder_y>271.0</left_shoulder_y>
			<right_shoulder_x>1340.6</right_shoulder_x>
			<right_shoulder_y>283.6</right_shoulder_y>
			<neck_x>1296.20560748</neck_x>
			<neck_y>266.0</neck_y>
		</keypoints>
	</object>
	<object>
		<name>person</name>
		<pose>Unspecified</pose>
		<truncated>0</truncated>
		<difficult>0</difficult>
		<occluded>0</occluded>
		<confidence>1</confidence>
		<bndbox>
			<xmin>1114</xmin>
			<ymin>189</ymin>
			<xmax>1199</xmax>
			<ymax>269</ymax>
		</bndbox>
		<keypoints>
			<cent_x>1145.0</cent_x>
			<cent_y>197.0</cent_y>
			<left_shoulder_x>1134.0</left_shoulder_x>
			<left_shoulder_y>246.0</left_shoulder_y>
			<right_shoulder_x>1182.0</right_shoulder_x>
			<right_shoulder_y>253.0</right_shoulder_y>
			<neck_x>1152.0</neck_x>
			<neck_y>235.0</neck_y>
		</keypoints>
	</object>
	<object>
		<name>person</name>
		<pose>Unspecified</pose>
		<truncated>0</truncated>
		<difficult>0</difficult>
		<occluded>0</occluded>
		<confidence>1</confidence>
		<bndbox>
			<xmin>973</xmin>
			<ymin>131</ymin>
			<xmax>1028</xmax>
			<ymax>197</ymax>
		</bndbox>
		<keypoints>
			<cent_x>1000.5</cent_x>
			<cent_y>157.4</cent_y>
			<left_shoulder_x>1008.0</left_shoulder_x>
			<left_shoulder_y>149.0</left_shoulder_y>
			<right_shoulder_x>1015.0</right_shoulder_x>
			<right_shoulder_y>176.0</right_shoulder_y>
			<neck_x>998.0</neck_x>
			<neck_y>170.0</neck_y>
		</keypoints>
	</object>
	<object>
		<name>person</name>
		<pose>Unspecified</pose>
		<truncated>0</truncated>
		<difficult>0</difficult>
		<occluded>0</occluded>
		<confidence>1</confidence>
		<bndbox>
			<xmin>888</xmin>
			<ymin>153</ymin>
			<xmax>974</xmax>
			<ymax>208</ymax>
		</bndbox>
		<keypoints>
			<cent_x>937.0</cent_x>
			<cent_y>160.0</cent_y>
			<left_shoulder_x>910.0</left_shoulder_x>
			<left_shoulder_y>188.0</left_shoulder_y>
			<right_shoulder_x>956.8</right_shoulder_x>
			<right_shoulder_y>197.0</right_shoulder_y>
			<neck_x>939.0</neck_x>
			<neck_y>188.0</neck_y>
		</keypoints>
	</object>
</annotation>
