<?xml version="1.0" ?>
<annotation>
	<folder>VideoData</folder>
	<source>
		<database>Video Data</database>
		<annotation>PASCAL 2012</annotation>
	</source>
	<owner>
		<name>samuel</name>
	</owner>
	<size>
		<width>1920</width>
		<height>1080</height>
		<depth>3</depth>
	</size>
	<segmented>0</segmented>
	<object>
		<name>person</name>
		<pose>Unspecified</pose>
		<truncated>0</truncated>
		<difficult>0</difficult>
		<occluded>0</occluded>
		<confidence>1</confidence>
		<bndbox>
			<xmin>668</xmin>
			<ymin>8</ymin>
			<xmax>727</xmax>
			<ymax>52</ymax>
		</bndbox>
		<keypoints>
			<cent_x>702.666666667</cent_x>
			<cent_y>22.6666666667</cent_y>
			<left_shoulder_x>-1.0</left_shoulder_x>
			<left_shoulder_y>-1.0</left_shoulder_y>
			<right_shoulder_x>686.0</right_shoulder_x>
			<right_shoulder_y>42.6666666667</right_shoulder_y>
			<neck_x>684.0</neck_x>
			<neck_y>30.0</neck_y>
		</keypoints>
	</object>
	<object>
		<name>person</name>
		<pose>Unspecified</pose>
		<truncated>0</truncated>
		<difficult>0</difficult>
		<occluded>0</occluded>
		<confidence>1</confidence>
		<bndbox>
			<xmin>796</xmin>
			<ymin>12</ymin>
			<xmax>866</xmax>
			<ymax>54</ymax>
		</bndbox>
		<keypoints>
			<cent_x>832.666666667</cent_x>
			<cent_y>22.0</cent_y>
			<left_shoulder_x>804.0</left_shoulder_x>
			<left_shoulder_y>38.6666666667</left_shoulder_y>
			<right_shoulder_x>856.0</right_shoulder_x>
			<right_shoulder_y>37.3333333333</right_shoulder_y>
			<neck_x>831.333333333</neck_x>
			<neck_y>30.6666666667</neck_y>
		</keypoints>
	</object>
	<object>
		<name>person</name>
		<pose>Unspecified</pose>
		<truncated>0</truncated>
		<difficult>0</difficult>
		<occluded>0</occluded>
		<confidence>1</confidence>
		<bndbox>
			<xmin>861</xmin>
			<ymin>0</ymin>
			<xmax>918</xmax>
			<ymax>38</ymax>
		</bndbox>
		<keypoints>
			<cent_x>884.666666667</cent_x>
			<cent_y>15.3333333333</cent_y>
			<left_shoulder_x>908.0</left_shoulder_x>
			<left_shoulder_y>18.6666666667</left_shoulder_y>
			<right_shoulder_x>868.666666667</right_shoulder_x>
			<right_shoulder_y>22.0</right_shoulder_y>
			<neck_x>886.666666667</neck_x>
			<neck_y>24.0</neck_y>
		</keypoints>
	</object>
	<object>
		<name>person</name>
		<pose>Unspecified</pose>
		<truncated>0</truncated>
		<difficult>0</difficult>
		<occluded>0</occluded>
		<confidence>1</confidence>
		<bndbox>
			<xmin>935</xmin>
			<ymin>2</ymin>
			<xmax>994</xmax>
			<ymax>46</ymax>
		</bndbox>
		<keypoints>
			<cent_x>963.333333333</cent_x>
			<cent_y>15.3333333333</cent_y>
			<left_shoulder_x>940.0</left_shoulder_x>
			<left_shoulder_y>35.3333333333</left_shoulder_y>
			<right_shoulder_x>988.0</right_shoulder_x>
			<right_shoulder_y>36.0</right_shoulder_y>
			<neck_x>967.333333333</neck_x>
			<neck_y>34.0</neck_y>
		</keypoints>
	</object>
	<object>
		<name>person</name>
		<pose>Unspecified</pose>
		<truncated>0</truncated>
		<difficult>0</difficult>
		<occluded>0</occluded>
		<confidence>1</confidence>
		<bndbox>
			<xmin>979</xmin>
			<ymin>10</ymin>
			<xmax>1037</xmax>
			<ymax>60</ymax>
		</bndbox>
		<keypoints>
			<cent_x>1009.33333333</cent_x>
			<cent_y>27.3333333333</cent_y>
			<left_shoulder_x>987.333333333</left_shoulder_x>
			<left_shoulder_y>46.0</left_shoulder_y>
			<right_shoulder_x>1026.0</right_shoulder_x>
			<right_shoulder_y>48.0</right_shoulder_y>
			<neck_x>1001.33333333</neck_x>
			<neck_y>41.3333333333</neck_y>
		</keypoints>
	</object>
	<object>
		<name>person</name>
		<pose>Unspecified</pose>
		<truncated>0</truncated>
		<difficult>0</difficult>
		<occluded>0</occluded>
		<confidence>1</confidence>
		<bndbox>
			<xmin>1124</xmin>
			<ymin>34</ymin>
			<xmax>1197</xmax>
			<ymax>88</ymax>
		</bndbox>
		<keypoints>
			<cent_x>1170.0</cent_x>
			<cent_y>60.0</cent_y>
			<left_shoulder_x>-1.0</left_shoulder_x>
			<left_shoulder_y>-1.0</left_shoulder_y>
			<right_shoulder_x>1132.66666667</right_shoulder_x>
			<right_shoulder_y>68.6666666667</right_shoulder_y>
			<neck_x>1170.0</neck_x>
			<neck_y>73.3333333333</neck_y>
		</keypoints>
	</object>
</annotation>
