<?xml version="1.0" ?>
<annotation>
	<folder>VideoData</folder>
	<source>
		<database>Video Data</database>
		<annotation>PASCAL 2012</annotation>
	</source>
	<owner>
		<name>samuel</name>
	</owner>
	<size>
		<width>1920</width>
		<height>1080</height>
		<depth>3</depth>
	</size>
	<segmented>0</segmented>
	<object>
		<name>person</name>
		<pose>Unspecified</pose>
		<truncated>0</truncated>
		<difficult>0</difficult>
		<occluded>0</occluded>
		<confidence>1</confidence>
		<bndbox>
			<xmin>1692</xmin>
			<ymin>586</ymin>
			<xmax>1841</xmax>
			<ymax>729</ymax>
		</bndbox>
		<keypoints>
			<cent_x>1749.14285714</cent_x>
			<cent_y>632.571428571</cent_y>
			<left_shoulder_x>1718.85714286</left_shoulder_x>
			<left_shoulder_y>717.714285714</left_shoulder_y>
			<right_shoulder_x>1818.28571429</right_shoulder_x>
			<right_shoulder_y>692.0</right_shoulder_y>
			<neck_x>-1.0</neck_x>
			<neck_y>-1.0</neck_y>
		</keypoints>
	</object>
	<object>
		<name>person</name>
		<pose>Unspecified</pose>
		<truncated>0</truncated>
		<difficult>0</difficult>
		<occluded>0</occluded>
		<confidence>1</confidence>
		<bndbox>
			<xmin>1143</xmin>
			<ymin>576</ymin>
			<xmax>1348</xmax>
			<ymax>745</ymax>
		</bndbox>
		<keypoints>
			<cent_x>1273.71428571</cent_x>
			<cent_y>624.571428571</cent_y>
			<left_shoulder_x>1147.0137781</left_shoulder_x>
			<left_shoulder_y>700.571428571</left_shoulder_y>
			<right_shoulder_x>1318.26831037</right_shoulder_x>
			<right_shoulder_y>732.571428571</right_shoulder_y>
			<neck_x>1244.57142857</neck_x>
			<neck_y>680.0</neck_y>
		</keypoints>
	</object>
	<object>
		<name>person</name>
		<pose>Unspecified</pose>
		<truncated>0</truncated>
		<difficult>0</difficult>
		<occluded>0</occluded>
		<confidence>1</confidence>
		<bndbox>
			<xmin>1261</xmin>
			<ymin>485</ymin>
			<xmax>1384</xmax>
			<ymax>597</ymax>
		</bndbox>
		<keypoints>
			<cent_x>1347.42857143</cent_x>
			<cent_y>542.857142857</cent_y>
			<left_shoulder_x>1370.28571429</left_shoulder_x>
			<left_shoulder_y>575.428571429</left_shoulder_y>
			<right_shoulder_x>-1.0</right_shoulder_x>
			<right_shoulder_y>-1.0</right_shoulder_y>
			<neck_x>1317.14285714</neck_x>
			<neck_y>570.285714286</neck_y>
		</keypoints>
	</object>
	<object>
		<name>person</name>
		<pose>Unspecified</pose>
		<truncated>0</truncated>
		<difficult>0</difficult>
		<occluded>0</occluded>
		<confidence>1</confidence>
		<bndbox>
			<xmin>1160</xmin>
			<ymin>275</ymin>
			<xmax>1200</xmax>
			<ymax>299</ymax>
		</bndbox>
		<keypoints>
			<cent_x>1180.0</cent_x>
			<cent_y>284.6</cent_y>
			<left_shoulder_x>1168.0</left_shoulder_x>
			<left_shoulder_y>294.2</left_shoulder_y>
			<right_shoulder_x>1192.0</right_shoulder_x>
			<right_shoulder_y>294.2</right_shoulder_y>
			<neck_x>-1.0</neck_x>
			<neck_y>-1.0</neck_y>
		</keypoints>
	</object>
	<object>
		<name>person</name>
		<pose>Unspecified</pose>
		<truncated>0</truncated>
		<difficult>0</difficult>
		<occluded>0</occluded>
		<confidence>1</confidence>
		<bndbox>
			<xmin>1077</xmin>
			<ymin>357</ymin>
			<xmax>1159</xmax>
			<ymax>422</ymax>
		</bndbox>
		<keypoints>
			<cent_x>1118.85714286</cent_x>
			<cent_y>388.0</cent_y>
			<left_shoulder_x>1155.42857143</left_shoulder_x>
			<left_shoulder_y>411.428571429</left_shoulder_y>
			<right_shoulder_x>1082.85714286</right_shoulder_x>
			<right_shoulder_y>411.428571429</right_shoulder_y>
			<neck_x>1122.28571429</neck_x>
			<neck_y>407.428571429</neck_y>
		</keypoints>
	</object>
	<object>
		<name>person</name>
		<pose>Unspecified</pose>
		<truncated>0</truncated>
		<difficult>0</difficult>
		<occluded>0</occluded>
		<confidence>1</confidence>
		<bndbox>
			<xmin>1080</xmin>
			<ymin>282</ymin>
			<xmax>1125</xmax>
			<ymax>328</ymax>
		</bndbox>
		<keypoints>
			<cent_x>1111.42857143</cent_x>
			<cent_y>303.428571429</cent_y>
			<left_shoulder_x>-1.0</left_shoulder_x>
			<left_shoulder_y>-1.0</left_shoulder_y>
			<right_shoulder_x>1094.85714286</right_shoulder_x>
			<right_shoulder_y>320.0</right_shoulder_y>
			<neck_x>-1.0</neck_x>
			<neck_y>-1.0</neck_y>
		</keypoints>
	</object>
	<object>
		<name>person</name>
		<pose>Unspecified</pose>
		<truncated>0</truncated>
		<difficult>0</difficult>
		<occluded>0</occluded>
		<confidence>1</confidence>
		<bndbox>
			<xmin>839</xmin>
			<ymin>227</ymin>
			<xmax>873</xmax>
			<ymax>252</ymax>
		</bndbox>
		<keypoints>
			<cent_x>856.0</cent_x>
			<cent_y>237.0</cent_y>
			<left_shoulder_x>845.8</left_shoulder_x>
			<left_shoulder_y>247.0</left_shoulder_y>
			<right_shoulder_x>866.2</right_shoulder_x>
			<right_shoulder_y>247.0</right_shoulder_y>
			<neck_x>-1.0</neck_x>
			<neck_y>-1.0</neck_y>
		</keypoints>
	</object>
	<object>
		<name>person</name>
		<pose>Unspecified</pose>
		<truncated>0</truncated>
		<difficult>0</difficult>
		<occluded>0</occluded>
		<confidence>1</confidence>
		<bndbox>
			<xmin>925</xmin>
			<ymin>313</ymin>
			<xmax>1009</xmax>
			<ymax>383</ymax>
		</bndbox>
		<keypoints>
			<cent_x>964.0</cent_x>
			<cent_y>337.142857143</cent_y>
			<left_shoulder_x>1000.57142857</left_shoulder_x>
			<left_shoulder_y>369.714285714</left_shoulder_y>
			<right_shoulder_x>-1.0</right_shoulder_x>
			<right_shoulder_y>-1.0</right_shoulder_y>
			<neck_x>970.857142857</neck_x>
			<neck_y>358.285714286</neck_y>
		</keypoints>
	</object>
	<object>
		<name>person</name>
		<pose>Unspecified</pose>
		<truncated>0</truncated>
		<difficult>0</difficult>
		<occluded>0</occluded>
		<confidence>1</confidence>
		<bndbox>
			<xmin>778</xmin>
			<ymin>343</ymin>
			<xmax>875</xmax>
			<ymax>409</ymax>
		</bndbox>
		<keypoints>
			<cent_x>833.714285714</cent_x>
			<cent_y>378.285714286</cent_y>
			<left_shoulder_x>864.0</left_shoulder_x>
			<left_shoulder_y>394.285714286</left_shoulder_y>
			<right_shoulder_x>792.571428571</right_shoulder_x>
			<right_shoulder_y>401.714285714</right_shoulder_y>
			<neck_x>829.142857143</neck_x>
			<neck_y>394.285714286</neck_y>
		</keypoints>
	</object>
</annotation>
