<?xml version="1.0" ?>
<annotation>
	<folder>VideoData</folder>
	<source>
		<database>Video Data</database>
		<annotation>PASCAL 2012</annotation>
	</source>
	<owner>
		<name>samuel</name>
	</owner>
	<size>
		<width>1920</width>
		<height>1080</height>
		<depth>3</depth>
	</size>
	<segmented>0</segmented>
	<object>
		<name>person</name>
		<pose>Unspecified</pose>
		<truncated>0</truncated>
		<difficult>0</difficult>
		<occluded>0</occluded>
		<confidence>1</confidence>
		<bndbox>
			<xmin>906</xmin>
			<ymin>54</ymin>
			<xmax>1040</xmax>
			<ymax>150</ymax>
		</bndbox>
		<keypoints>
			<cent_x>1005.0</cent_x>
			<cent_y>80.0</cent_y>
			<left_shoulder_x>-1.0</left_shoulder_x>
			<left_shoulder_y>-1.0</left_shoulder_y>
			<right_shoulder_x>966.666666667</right_shoulder_x>
			<right_shoulder_y>121.666666667</right_shoulder_y>
			<neck_x>976.666666667</neck_x>
			<neck_y>95.0</neck_y>
		</keypoints>
	</object>
	<object>
		<name>person</name>
		<pose>Unspecified</pose>
		<truncated>0</truncated>
		<difficult>0</difficult>
		<occluded>0</occluded>
		<confidence>1</confidence>
		<bndbox>
			<xmin>995</xmin>
			<ymin>37</ymin>
			<xmax>1127</xmax>
			<ymax>115</ymax>
		</bndbox>
		<keypoints>
			<cent_x>1091.66666667</cent_x>
			<cent_y>66.6666666667</cent_y>
			<left_shoulder_x>-1.0</left_shoulder_x>
			<left_shoulder_y>-1.0</left_shoulder_y>
			<right_shoulder_x>1110.0</right_shoulder_x>
			<right_shoulder_y>93.3333333333</right_shoulder_y>
			<neck_x>1058.33333333</neck_x>
			<neck_y>80.0</neck_y>
		</keypoints>
	</object>
	<object>
		<name>person</name>
		<pose>Unspecified</pose>
		<truncated>0</truncated>
		<difficult>0</difficult>
		<occluded>0</occluded>
		<confidence>1</confidence>
		<bndbox>
			<xmin>1431</xmin>
			<ymin>313</ymin>
			<xmax>1600</xmax>
			<ymax>490</ymax>
		</bndbox>
		<keypoints>
			<cent_x>1526.66666667</cent_x>
			<cent_y>360.0</cent_y>
			<left_shoulder_x>-1.0</left_shoulder_x>
			<left_shoulder_y>-1.0</left_shoulder_y>
			<right_shoulder_x>1541.66666667</right_shoulder_x>
			<right_shoulder_y>445.0</right_shoulder_y>
			<neck_x>1515.0</neck_x>
			<neck_y>401.666666667</neck_y>
		</keypoints>
	</object>
	<object>
		<name>person</name>
		<pose>Unspecified</pose>
		<truncated>0</truncated>
		<difficult>0</difficult>
		<occluded>0</occluded>
		<confidence>1</confidence>
		<bndbox>
			<xmin>1478</xmin>
			<ymin>506</ymin>
			<xmax>1677</xmax>
			<ymax>720</ymax>
		</bndbox>
		<keypoints>
			<cent_x>1606.66666667</cent_x>
			<cent_y>566.666666667</cent_y>
			<left_shoulder_x>1503.33333333</left_shoulder_x>
			<left_shoulder_y>591.666666667</left_shoulder_y>
			<right_shoulder_x>1626.66666667</right_shoulder_x>
			<right_shoulder_y>681.666666667</right_shoulder_y>
			<neck_x>1590.0</neck_x>
			<neck_y>618.333333333</neck_y>
		</keypoints>
	</object>
</annotation>
