<?xml version="1.0" ?>
<annotation>
	<folder>VideoData</folder>
	<source>
		<database>Video Data</database>
		<annotation>PASCAL 2012</annotation>
	</source>
	<owner>
		<name>samuel</name>
	</owner>
	<size>
		<width>1920</width>
		<height>1080</height>
		<depth>3</depth>
	</size>
	<segmented>0</segmented>
	<object>
		<name>person</name>
		<pose>Unspecified</pose>
		<truncated>0</truncated>
		<difficult>0</difficult>
		<occluded>0</occluded>
		<confidence>1</confidence>
		<bndbox>
			<xmin>488</xmin>
			<ymin>68</ymin>
			<xmax>632</xmax>
			<ymax>188</ymax>
		</bndbox>
		<keypoints>
			<cent_x>543.880597015</cent_x>
			<cent_y>91.6666666667</cent_y>
			<left_shoulder_x>502.686567164</left_shoulder_x>
			<left_shoulder_y>151.666666667</left_shoulder_y>
			<right_shoulder_x>628.059701493</right_shoulder_x>
			<right_shoulder_y>145.0</right_shoulder_y>
			<neck_x>549.253731343</neck_x>
			<neck_y>143.333333333</neck_y>
		</keypoints>
	</object>
	<object>
		<name>person</name>
		<pose>Unspecified</pose>
		<truncated>0</truncated>
		<difficult>0</difficult>
		<occluded>0</occluded>
		<confidence>1</confidence>
		<bndbox>
			<xmin>260</xmin>
			<ymin>115</ymin>
			<xmax>405</xmax>
			<ymax>232</ymax>
		</bndbox>
		<keypoints>
			<cent_x>331.666666667</cent_x>
			<cent_y>145.0</cent_y>
			<left_shoulder_x>278.333333333</left_shoulder_x>
			<left_shoulder_y>195.0</left_shoulder_y>
			<right_shoulder_x>386.666666667</right_shoulder_x>
			<right_shoulder_y>183.333333333</right_shoulder_y>
			<neck_x>325.0</neck_x>
			<neck_y>190.0</neck_y>
		</keypoints>
	</object>
	<object>
		<name>person</name>
		<pose>Unspecified</pose>
		<truncated>0</truncated>
		<difficult>0</difficult>
		<occluded>0</occluded>
		<confidence>1</confidence>
		<bndbox>
			<xmin>765</xmin>
			<ymin>221</ymin>
			<xmax>877</xmax>
			<ymax>364</ymax>
		</bndbox>
		<keypoints>
			<cent_x>818.333333333</cent_x>
			<cent_y>251.666666667</cent_y>
			<left_shoulder_x>-1.0</left_shoulder_x>
			<left_shoulder_y>-1.0</left_shoulder_y>
			<right_shoulder_x>846.666666667</right_shoulder_x>
			<right_shoulder_y>331.666666667</right_shoulder_y>
			<neck_x>815.0</neck_x>
			<neck_y>298.333333333</neck_y>
		</keypoints>
	</object>
	<object>
		<name>person</name>
		<pose>Unspecified</pose>
		<truncated>0</truncated>
		<difficult>0</difficult>
		<occluded>0</occluded>
		<confidence>1</confidence>
		<bndbox>
			<xmin>1508</xmin>
			<ymin>493</ymin>
			<xmax>1701</xmax>
			<ymax>698</ymax>
		</bndbox>
		<keypoints>
			<cent_x>1631.7981982</cent_x>
			<cent_y>539.700167504</cent_y>
			<left_shoulder_x>1526.66666667</left_shoulder_x>
			<left_shoulder_y>558.333333333</left_shoulder_y>
			<right_shoulder_x>1657.87927928</right_shoulder_x>
			<right_shoulder_y>665.035175879</right_shoulder_y>
			<neck_x>1607.45585586</neck_x>
			<neck_y>601.50921273</neck_y>
		</keypoints>
	</object>
</annotation>
