<?xml version="1.0" ?>
<annotation>
	<folder>VideoData</folder>
	<source>
		<database>Video Data</database>
		<annotation>PASCAL 2012</annotation>
	</source>
	<owner>
		<name>samuel</name>
	</owner>
	<size>
		<width>1920</width>
		<height>1080</height>
		<depth>3</depth>
	</size>
	<segmented>0</segmented>
	<object>
		<name>person</name>
		<pose>Unspecified</pose>
		<truncated>0</truncated>
		<difficult>0</difficult>
		<occluded>0</occluded>
		<confidence>1</confidence>
		<bndbox>
			<xmin>741</xmin>
			<ymin>11</ymin>
			<xmax>878</xmax>
			<ymax>116</ymax>
		</bndbox>
		<keypoints>
			<cent_x>831.666666667</cent_x>
			<cent_y>28.3333333333</cent_y>
			<left_shoulder_x>766.666666667</left_shoulder_x>
			<left_shoulder_y>85.0</left_shoulder_y>
			<right_shoulder_x>-1.0</right_shoulder_x>
			<right_shoulder_y>-1.0</right_shoulder_y>
			<neck_x>803.333333333</neck_x>
			<neck_y>53.3333333333</neck_y>
		</keypoints>
	</object>
	<object>
		<name>person</name>
		<pose>Unspecified</pose>
		<truncated>0</truncated>
		<difficult>0</difficult>
		<occluded>0</occluded>
		<confidence>1</confidence>
		<bndbox>
			<xmin>861</xmin>
			<ymin>3</ymin>
			<xmax>983</xmax>
			<ymax>70</ymax>
		</bndbox>
		<keypoints>
			<cent_x>948.333333333</cent_x>
			<cent_y>13.3333333333</cent_y>
			<left_shoulder_x>876.666666667</left_shoulder_x>
			<left_shoulder_y>35.0</left_shoulder_y>
			<right_shoulder_x>968.333333333</right_shoulder_x>
			<right_shoulder_y>35.0</right_shoulder_y>
			<neck_x>925.0</neck_x>
			<neck_y>26.6666666667</neck_y>
		</keypoints>
	</object>
	<object>
		<name>person</name>
		<pose>Unspecified</pose>
		<truncated>0</truncated>
		<difficult>0</difficult>
		<occluded>0</occluded>
		<confidence>1</confidence>
		<bndbox>
			<xmin>1023</xmin>
			<ymin>10</ymin>
			<xmax>1120</xmax>
			<ymax>67</ymax>
		</bndbox>
		<keypoints>
			<cent_x>1048.33333333</cent_x>
			<cent_y>31.6666666667</cent_y>
			<left_shoulder_x>-1.0</left_shoulder_x>
			<left_shoulder_y>-1.0</left_shoulder_y>
			<right_shoulder_x>1091.66666667</right_shoulder_x>
			<right_shoulder_y>30.0</right_shoulder_y>
			<neck_x>1066.66666667</neck_x>
			<neck_y>38.3333333333</neck_y>
		</keypoints>
	</object>
	<object>
		<name>person</name>
		<pose>Unspecified</pose>
		<truncated>0</truncated>
		<difficult>0</difficult>
		<occluded>0</occluded>
		<confidence>1</confidence>
		<bndbox>
			<xmin>770</xmin>
			<ymin>238</ymin>
			<xmax>924</xmax>
			<ymax>402</ymax>
		</bndbox>
		<keypoints>
			<cent_x>836.666666667</cent_x>
			<cent_y>261.666666667</cent_y>
			<left_shoulder_x>-1.0</left_shoulder_x>
			<left_shoulder_y>-1.0</left_shoulder_y>
			<right_shoulder_x>866.666666667</right_shoulder_x>
			<right_shoulder_y>348.333333333</right_shoulder_y>
			<neck_x>823.333333333</neck_x>
			<neck_y>310.0</neck_y>
		</keypoints>
	</object>
	<object>
		<name>person</name>
		<pose>Unspecified</pose>
		<truncated>0</truncated>
		<difficult>0</difficult>
		<occluded>0</occluded>
		<confidence>1</confidence>
		<bndbox>
			<xmin>1446</xmin>
			<ymin>518</ymin>
			<xmax>1651</xmax>
			<ymax>713</ymax>
		</bndbox>
		<keypoints>
			<cent_x>1565.0</cent_x>
			<cent_y>566.666666667</cent_y>
			<left_shoulder_x>-1.0</left_shoulder_x>
			<left_shoulder_y>-1.0</left_shoulder_y>
			<right_shoulder_x>1610.0</right_shoulder_x>
			<right_shoulder_y>674.0</right_shoulder_y>
			<neck_x>1550.0</neck_x>
			<neck_y>630.0</neck_y>
		</keypoints>
	</object>
</annotation>
