<?xml version="1.0" ?>
<annotation>
	<folder>VideoData</folder>
	<source>
		<database>Video Data</database>
		<annotation>PASCAL 2012</annotation>
	</source>
	<owner>
		<name>samuel</name>
	</owner>
	<size>
		<width>1920</width>
		<height>1080</height>
		<depth>3</depth>
	</size>
	<segmented>0</segmented>
	<object>
		<name>person</name>
		<pose>Unspecified</pose>
		<truncated>0</truncated>
		<difficult>0</difficult>
		<occluded>0</occluded>
		<confidence>1</confidence>
		<bndbox>
			<xmin>526</xmin>
			<ymin>2</ymin>
			<xmax>755</xmax>
			<ymax>119</ymax>
		</bndbox>
		<keypoints>
			<cent_x>576.0</cent_x>
			<cent_y>30.0</cent_y>
			<left_shoulder_x>-1.0</left_shoulder_x>
			<left_shoulder_y>-1.0</left_shoulder_y>
			<right_shoulder_x>714.0</right_shoulder_x>
			<right_shoulder_y>84.0</right_shoulder_y>
			<neck_x>646.0</neck_x>
			<neck_y>30.0</neck_y>
		</keypoints>
	</object>
	<object>
		<name>person</name>
		<pose>Unspecified</pose>
		<truncated>0</truncated>
		<difficult>0</difficult>
		<occluded>0</occluded>
		<confidence>1</confidence>
		<bndbox>
			<xmin>770</xmin>
			<ymin>588</ymin>
			<xmax>969</xmax>
			<ymax>799</ymax>
		</bndbox>
		<keypoints>
			<cent_x>878.0</cent_x>
			<cent_y>748.0</cent_y>
			<left_shoulder_x>790.0</left_shoulder_x>
			<left_shoulder_y>728.0</left_shoulder_y>
			<right_shoulder_x>952.0</right_shoulder_x>
			<right_shoulder_y>626.0</right_shoulder_y>
			<neck_x>890.0</neck_x>
			<neck_y>658.0</neck_y>
		</keypoints>
	</object>
	<object>
		<name>person</name>
		<pose>Unspecified</pose>
		<truncated>0</truncated>
		<difficult>0</difficult>
		<occluded>0</occluded>
		<confidence>1</confidence>
		<bndbox>
			<xmin>642</xmin>
			<ymin>952</ymin>
			<xmax>871</xmax>
			<ymax>1073</ymax>
		</bndbox>
		<keypoints>
			<cent_x>696.0</cent_x>
			<cent_y>1054.0</cent_y>
			<left_shoulder_x>-1.0</left_shoulder_x>
			<left_shoulder_y>-1.0</left_shoulder_y>
			<right_shoulder_x>814.0</right_shoulder_x>
			<right_shoulder_y>990.0</right_shoulder_y>
			<neck_x>764.0</neck_x>
			<neck_y>1056.0</neck_y>
		</keypoints>
	</object>
</annotation>
