<?xml version="1.0" ?>
<annotation>
	<folder>VideoData</folder>
	<source>
		<database>Video Data</database>
		<annotation>PASCAL 2012</annotation>
	</source>
	<owner>
		<name>samuel</name>
	</owner>
	<size>
		<width>1920</width>
		<height>1080</height>
		<depth>3</depth>
	</size>
	<segmented>0</segmented>
	<object>
		<name>person</name>
		<pose>Unspecified</pose>
		<truncated>0</truncated>
		<difficult>0</difficult>
		<occluded>0</occluded>
		<confidence>1</confidence>
		<bndbox>
			<xmin>905</xmin>
			<ymin>392</ymin>
			<xmax>1123</xmax>
			<ymax>519</ymax>
		</bndbox>
		<keypoints>
			<cent_x>998.181818182</cent_x>
			<cent_y>454.545454545</cent_y>
			<left_shoulder_x>1096.36363636</left_shoulder_x>
			<left_shoulder_y>399.760059613</left_shoulder_y>
			<right_shoulder_x>914.545454545</right_shoulder_x>
			<right_shoulder_y>445.184798808</right_shoulder_y>
			<neck_x>1030.90909091</neck_x>
			<neck_y>403.636363636</neck_y>
		</keypoints>
	</object>
	<object>
		<name>person</name>
		<pose>Unspecified</pose>
		<truncated>0</truncated>
		<difficult>0</difficult>
		<occluded>0</occluded>
		<confidence>1</confidence>
		<bndbox>
			<xmin>907</xmin>
			<ymin>898</ymin>
			<xmax>1071</xmax>
			<ymax>1076</ymax>
		</bndbox>
		<keypoints>
			<cent_x>965.454545455</cent_x>
			<cent_y>1035.73809524</cent_y>
			<left_shoulder_x>1050.90909091</left_shoulder_x>
			<left_shoulder_y>1064.63419913</left_shoulder_y>
			<right_shoulder_x>1021.81818182</right_shoulder_x>
			<right_shoulder_y>907.272727273</right_shoulder_y>
			<neck_x>1030.90909091</neck_x>
			<neck_y>1005.45454545</neck_y>
		</keypoints>
	</object>
	<object>
		<name>person</name>
		<pose>Unspecified</pose>
		<truncated>0</truncated>
		<difficult>0</difficult>
		<occluded>0</occluded>
		<confidence>1</confidence>
		<bndbox>
			<xmin>501</xmin>
			<ymin>799</ymin>
			<xmax>716</xmax>
			<ymax>959</ymax>
		</bndbox>
		<keypoints>
			<cent_x>576.363636364</cent_x>
			<cent_y>910.909090909</cent_y>
			<left_shoulder_x>-1.0</left_shoulder_x>
			<left_shoulder_y>-1.0</left_shoulder_y>
			<right_shoulder_x>689.090909091</right_shoulder_x>
			<right_shoulder_y>816.363636364</right_shoulder_y>
			<neck_x>643.636363636</neck_x>
			<neck_y>858.181818182</neck_y>
		</keypoints>
	</object>
	<object>
		<name>person</name>
		<pose>Unspecified</pose>
		<truncated>0</truncated>
		<difficult>0</difficult>
		<occluded>0</occluded>
		<confidence>1</confidence>
		<bndbox>
			<xmin>1</xmin>
			<ymin>30</ymin>
			<xmax>178</xmax>
			<ymax>190</ymax>
		</bndbox>
		<keypoints>
			<cent_x>89.0909090909</cent_x>
			<cent_y>129.090909091</cent_y>
			<left_shoulder_x>150.909090909</left_shoulder_x>
			<left_shoulder_y>72.7272727273</left_shoulder_y>
			<right_shoulder_x>-1.0</right_shoulder_x>
			<right_shoulder_y>-1.0</right_shoulder_y>
			<neck_x>107.272727273</neck_x>
			<neck_y>74.5454545455</neck_y>
		</keypoints>
	</object>
</annotation>
