<?xml version="1.0" ?>
<annotation>
	<folder>VideoData</folder>
	<source>
		<database>Video Data</database>
		<annotation>PASCAL 2012</annotation>
	</source>
	<owner>
		<name>samuel</name>
	</owner>
	<size>
		<width>1920</width>
		<height>1080</height>
		<depth>3</depth>
	</size>
	<segmented>0</segmented>
	<object>
		<name>person</name>
		<pose>Unspecified</pose>
		<truncated>0</truncated>
		<difficult>0</difficult>
		<occluded>0</occluded>
		<confidence>1</confidence>
		<bndbox>
			<xmin>1334</xmin>
			<ymin>938</ymin>
			<xmax>1580</xmax>
			<ymax>1078</ymax>
		</bndbox>
		<keypoints>
			<cent_x>1510.90909091</cent_x>
			<cent_y>1030.90909091</cent_y>
			<left_shoulder_x>1360.0</left_shoulder_x>
			<left_shoulder_y>1010.90909091</left_shoulder_y>
			<right_shoulder_x>-1.0</right_shoulder_x>
			<right_shoulder_y>-1.0</right_shoulder_y>
			<neck_x>1414.54545455</neck_x>
			<neck_y>1032.72727273</neck_y>
		</keypoints>
	</object>
	<object>
		<name>person</name>
		<pose>Unspecified</pose>
		<truncated>0</truncated>
		<difficult>0</difficult>
		<occluded>0</occluded>
		<confidence>1</confidence>
		<bndbox>
			<xmin>1018</xmin>
			<ymin>3</ymin>
			<xmax>1200</xmax>
			<ymax>147</ymax>
		</bndbox>
		<keypoints>
			<cent_x>1110.90909091</cent_x>
			<cent_y>105.454545455</cent_y>
			<left_shoulder_x>1190.90909091</left_shoulder_x>
			<left_shoulder_y>110.909090909</left_shoulder_y>
			<right_shoulder_x>1038.18181818</right_shoulder_x>
			<right_shoulder_y>78.1818181818</right_shoulder_y>
			<neck_x>-1.0</neck_x>
			<neck_y>-1.0</neck_y>
		</keypoints>
	</object>
	<object>
		<name>person</name>
		<pose>Unspecified</pose>
		<truncated>0</truncated>
		<difficult>0</difficult>
		<occluded>0</occluded>
		<confidence>1</confidence>
		<bndbox>
			<xmin>710</xmin>
			<ymin>779</ymin>
			<xmax>894</xmax>
			<ymax>999</ymax>
		</bndbox>
		<keypoints>
			<cent_x>781.818181818</cent_x>
			<cent_y>910.909090909</cent_y>
			<left_shoulder_x>794.545454545</left_shoulder_x>
			<left_shoulder_y>987.272727273</left_shoulder_y>
			<right_shoulder_x>858.181818182</right_shoulder_x>
			<right_shoulder_y>809.090909091</right_shoulder_y>
			<neck_x>829.090909091</neck_x>
			<neck_y>921.818181818</neck_y>
		</keypoints>
	</object>
	<object>
		<name>person</name>
		<pose>Unspecified</pose>
		<truncated>0</truncated>
		<difficult>0</difficult>
		<occluded>0</occluded>
		<confidence>1</confidence>
		<bndbox>
			<xmin>469</xmin>
			<ymin>467</ymin>
			<xmax>671</xmax>
			<ymax>678</ymax>
		</bndbox>
		<keypoints>
			<cent_x>530.909090909</cent_x>
			<cent_y>580.0</cent_y>
			<left_shoulder_x>623.636363636</left_shoulder_x>
			<left_shoulder_y>656.363636364</left_shoulder_y>
			<right_shoulder_x>598.181818182</right_shoulder_x>
			<right_shoulder_y>492.727272727</right_shoulder_y>
			<neck_x>605.454545455</neck_x>
			<neck_y>572.727272727</neck_y>
		</keypoints>
	</object>
	<object>
		<name>person</name>
		<pose>Unspecified</pose>
		<truncated>0</truncated>
		<difficult>0</difficult>
		<occluded>0</occluded>
		<confidence>1</confidence>
		<bndbox>
			<xmin>221</xmin>
			<ymin>174</ymin>
			<xmax>418</xmax>
			<ymax>392</ymax>
		</bndbox>
		<keypoints>
			<cent_x>367.272727273</cent_x>
			<cent_y>269.090909091</cent_y>
			<left_shoulder_x>372.727272727</left_shoulder_x>
			<left_shoulder_y>192.727272727</left_shoulder_y>
			<right_shoulder_x>350.909090909</right_shoulder_x>
			<right_shoulder_y>370.909090909</right_shoulder_y>
			<neck_x>327.272727273</neck_x>
			<neck_y>323.636363636</neck_y>
		</keypoints>
	</object>
</annotation>
