<?xml version="1.0" ?>
<annotation>
	<folder>VideoData</folder>
	<source>
		<database>Video Data</database>
		<annotation>PASCAL 2012</annotation>
	</source>
	<owner>
		<name>samuel</name>
	</owner>
	<size>
		<width>1920</width>
		<height>1080</height>
		<depth>3</depth>
	</size>
	<segmented>0</segmented>
	<object>
		<name>person</name>
		<pose>Unspecified</pose>
		<truncated>0</truncated>
		<difficult>0</difficult>
		<occluded>0</occluded>
		<confidence>1</confidence>
		<bndbox>
			<xmin>442</xmin>
			<ymin>260</ymin>
			<xmax>615</xmax>
			<ymax>473</ymax>
		</bndbox>
		<keypoints>
			<cent_x>528.5</cent_x>
			<cent_y>345.2</cent_y>
			<left_shoulder_x>-1.0</left_shoulder_x>
			<left_shoulder_y>-1.0</left_shoulder_y>
			<right_shoulder_x>502.857142857</right_shoulder_x>
			<right_shoulder_y>281.428571429</right_shoulder_y>
			<neck_x>528.5</neck_x>
			<neck_y>430.4</neck_y>
		</keypoints>
	</object>
	<object>
		<name>person</name>
		<pose>Unspecified</pose>
		<truncated>0</truncated>
		<difficult>0</difficult>
		<occluded>0</occluded>
		<confidence>1</confidence>
		<bndbox>
			<xmin>1210</xmin>
			<ymin>607</ymin>
			<xmax>1364</xmax>
			<ymax>818</ymax>
		</bndbox>
		<keypoints>
			<cent_x>1287.0</cent_x>
			<cent_y>691.4</cent_y>
			<left_shoulder_x>-1.0</left_shoulder_x>
			<left_shoulder_y>-1.0</left_shoulder_y>
			<right_shoulder_x>1284.28571429</right_shoulder_x>
			<right_shoulder_y>625.714285714</right_shoulder_y>
			<neck_x>1287.0</neck_x>
			<neck_y>775.8</neck_y>
		</keypoints>
	</object>
	<object>
		<name>person</name>
		<pose>Unspecified</pose>
		<truncated>0</truncated>
		<difficult>0</difficult>
		<occluded>0</occluded>
		<confidence>1</confidence>
		<bndbox>
			<xmin>244</xmin>
			<ymin>718</ymin>
			<xmax>418</xmax>
			<ymax>911</ymax>
		</bndbox>
		<keypoints>
			<cent_x>-1.0</cent_x>
			<cent_y>-1.0</cent_y>
			<left_shoulder_x>338.571428571</left_shoulder_x>
			<left_shoulder_y>752.857142857</left_shoulder_y>
			<right_shoulder_x>391.428571429</right_shoulder_x>
			<right_shoulder_y>887.142857143</right_shoulder_y>
			<neck_x>331.0</neck_x>
			<neck_y>872.4</neck_y>
		</keypoints>
	</object>
	<object>
		<name>person</name>
		<pose>Unspecified</pose>
		<truncated>0</truncated>
		<difficult>0</difficult>
		<occluded>0</occluded>
		<confidence>1</confidence>
		<bndbox>
			<xmin>551</xmin>
			<ymin>957</ymin>
			<xmax>722</xmax>
			<ymax>1073</ymax>
		</bndbox>
		<keypoints>
			<cent_x>-1.0</cent_x>
			<cent_y>-1.0</cent_y>
			<left_shoulder_x>570.0</left_shoulder_x>
			<left_shoulder_y>997.142857143</left_shoulder_y>
			<right_shoulder_x>687.8</right_shoulder_x>
			<right_shoulder_y>1049.8</right_shoulder_y>
			<neck_x>636.5</neck_x>
			<neck_y>1049.8</neck_y>
		</keypoints>
	</object>
</annotation>
