<?xml version="1.0" ?>
<annotation>
	<folder>VideoData</folder>
	<source>
		<database>Video Data</database>
		<annotation>PASCAL 2012</annotation>
	</source>
	<owner>
		<name>samuel</name>
	</owner>
	<size>
		<width>1920</width>
		<height>1080</height>
		<depth>3</depth>
	</size>
	<segmented>0</segmented>
	<object>
		<name>person</name>
		<pose>Unspecified</pose>
		<truncated>0</truncated>
		<difficult>0</difficult>
		<occluded>0</occluded>
		<confidence>1</confidence>
		<bndbox>
			<xmin>14</xmin>
			<ymin>444</ymin>
			<xmax>117</xmax>
			<ymax>663</ymax>
		</bndbox>
		<keypoints>
			<cent_x>-1.0</cent_x>
			<cent_y>-1.0</cent_y>
			<left_shoulder_x>6.0</left_shoulder_x>
			<left_shoulder_y>640.0</left_shoulder_y>
			<right_shoulder_x>42.0</right_shoulder_x>
			<right_shoulder_y>454.0</right_shoulder_y>
			<neck_x>56.0</neck_x>
			<neck_y>562.0</neck_y>
		</keypoints>
	</object>
	<object>
		<name>person</name>
		<pose>Unspecified</pose>
		<truncated>0</truncated>
		<difficult>0</difficult>
		<occluded>0</occluded>
		<confidence>1</confidence>
		<bndbox>
			<xmin>510</xmin>
			<ymin>384</ymin>
			<xmax>675</xmax>
			<ymax>577</ymax>
		</bndbox>
		<keypoints>
			<cent_x>574.0</cent_x>
			<cent_y>462.0</cent_y>
			<left_shoulder_x>524.0</left_shoulder_x>
			<left_shoulder_y>396.0</left_shoulder_y>
			<right_shoulder_x>632.0</right_shoulder_x>
			<right_shoulder_y>560.0</right_shoulder_y>
			<neck_x>-1.0</neck_x>
			<neck_y>-1.0</neck_y>
		</keypoints>
	</object>
	<object>
		<name>person</name>
		<pose>Unspecified</pose>
		<truncated>0</truncated>
		<difficult>0</difficult>
		<occluded>0</occluded>
		<confidence>1</confidence>
		<bndbox>
			<xmin>880</xmin>
			<ymin>632</ymin>
			<xmax>1097</xmax>
			<ymax>775</ymax>
		</bndbox>
		<keypoints>
			<cent_x>998.0</cent_x>
			<cent_y>710.0</cent_y>
			<left_shoulder_x>892.0</left_shoulder_x>
			<left_shoulder_y>720.0</left_shoulder_y>
			<right_shoulder_x>1082.0</right_shoulder_x>
			<right_shoulder_y>680.0</right_shoulder_y>
			<neck_x>-1.0</neck_x>
			<neck_y>-1.0</neck_y>
		</keypoints>
	</object>
</annotation>
